metr/__init__.py
metr/app.py
metr/config.py
metr/db.py
metr-0.2.1.dist-info/DESCRIPTION.rst
metr-0.2.1.dist-info/METADATA
metr-0.2.1.dist-info/RECORD
metr-0.2.1.dist-info/WHEEL
metr-0.2.1.dist-info/metadata.json
metr-0.2.1.dist-info/top_level.txt
